arz_api_extended/__init__.py
arz_api_extended/api.py
arz_api_extended/consts.py
arz_api_extended/exceptions.py
arz_api_extended/bypass_antibot/__init__.py
arz_api_extended/bypass_antibot/script.py
arz_api_extended/models/__init__.py
arz_api_extended/models/category_object.py
arz_api_extended/models/member_object.py
arz_api_extended/models/other.py
arz_api_extended/models/post_object.py
arz_api_extended/models/thread_object.py
arizona_forum_api_extended-1.1.dist-info/LICENSE
arizona_forum_api_extended-1.1.dist-info/METADATA
arizona_forum_api_extended-1.1.dist-info/WHEEL
arizona_forum_api_extended-1.1.dist-info/top_level.txt
arizona_forum_api_extended-1.1.dist-info/RECORD
