Metadata-Version: 2.1
Name: arizona-forum-api-extended
Version: 1.1
Summary: API для работы с форумом Arizona RP
Home-page: https://github.com/fakelag28/Arizona-Forum-API
Author: fakelag28
Author-email: fakelag712@gmail.com
Classifier: Programming Language :: Python :: 3
Classifier: License :: OSI Approved :: MIT License
Classifier: Operating System :: OS Independent
Requires-Python: >=3.6
License-File: LICENSE
Requires-Dist: requests
Requires-Dist: beautifulsoup4
Requires-Dist: lxml
